cpau/__init__.py
cpau/baseapp.py
cpau/cli.py
cpau/electric_meter.py
cpau/exceptions.py
cpau/meter.py
cpau/session.py
cpau/water_meter.py
cpau/watersmart_session.py
cpau-1.0.0.dist-info/licenses/LICENSE
cpau-1.0.0.dist-info/METADATA
cpau-1.0.0.dist-info/WHEEL
cpau-1.0.0.dist-info/entry_points.txt
cpau-1.0.0.dist-info/top_level.txt
cpau-1.0.0.dist-info/RECORD
