Metadata-Version: 2.4
Name: cpau
Version: 1.0.0
Summary: Python library and CLI tools for City of Palo Alto Utilities meter data
Author-email: Joe Sinnott <joe@jsinnott.net>
License: MIT
Project-URL: Homepage, https://github.com/jsinnott/cpau
Project-URL: Repository, https://github.com/jsinnott/cpau.git
Project-URL: Issues, https://github.com/jsinnott/cpau/issues
Classifier: Development Status :: 5 - Production/Stable
Classifier: Intended Audience :: Developers
Classifier: License :: OSI Approved :: MIT License
Classifier: Programming Language :: Python :: 3
Classifier: Programming Language :: Python :: 3.8
Classifier: Programming Language :: Python :: 3.9
Classifier: Programming Language :: Python :: 3.10
Classifier: Programming Language :: Python :: 3.11
Classifier: Programming Language :: Python :: 3.12
Requires-Python: >=3.8
License-File: LICENSE
Requires-Dist: requests>=2.31.0
Requires-Dist: coloredlogs>=15.0
Requires-Dist: humanfriendly>=10.0
Requires-Dist: playwright>=1.40.0
Provides-Extra: dev
Requires-Dist: pytest>=7.0; extra == "dev"
Requires-Dist: pytest-mock>=3.12.0; extra == "dev"
Requires-Dist: black; extra == "dev"
Requires-Dist: mypy; extra == "dev"
Requires-Dist: types-requests; extra == "dev"
Provides-Extra: test
Requires-Dist: pytest>=7.0; extra == "test"
Requires-Dist: pytest-mock>=3.12.0; extra == "test"
Provides-Extra: docs
Requires-Dist: sphinx>=7.0; extra == "docs"
Requires-Dist: sphinx-rtd-theme>=2.0; extra == "docs"
Requires-Dist: sphinx-autodoc-typehints>=1.24; extra == "docs"
Dynamic: license-file
